geas_ai/__init__.py
geas_ai/main.py
geas_ai/utils.py
geas_ai/commands/__init__.py
geas_ai/commands/agents.py
geas_ai/commands/init.py
geas_ai/commands/lifecycle.py
geas_ai/commands/seal.py
geas_ai/commands/status.py
geas_ai/commands/verify.py
geas_ai/core/__init__.py
geas_ai/core/content.py
geas_ai-0.1.1.dist-info/METADATA
geas_ai-0.1.1.dist-info/WHEEL
geas_ai-0.1.1.dist-info/entry_points.txt
geas_ai-0.1.1.dist-info/licenses/LICENSE-APACHE
geas_ai-0.1.1.dist-info/licenses/LICENSE-MIT
geas_ai-0.1.1.dist-info/RECORD
