Metadata-Version: 2.4
Name: geas-ai
Version: 0.1.1
Project-URL: Documentation, https://radema.github.io/geas-ai/
Author: Raul De Maio
License-File: LICENSE-APACHE
License-File: LICENSE-MIT
Requires-Python: >=3.10
Requires-Dist: pyyaml>=6.0.3
Requires-Dist: rich>=14.2.0
Requires-Dist: typer>=0.21.0
